comi/__init__.py
comi/main.py
comi-0.1.2.dist-info/entry_points.txt
comi-0.1.2.dist-info/WHEEL
comi-0.1.2.dist-info/METADATA
comi-0.1.2.dist-info/RECORD
