Metadata-Version: 2.1
Name: comi
Version: 0.1.2
Summary: 
Author: Eyal Levin
Author-email: eyalev@gmail.com
Requires-Python: >=3.6,<4.0
Classifier: Programming Language :: Python :: 3
Classifier: Programming Language :: Python :: 3.6
Classifier: Programming Language :: Python :: 3.7
Classifier: Programming Language :: Python :: 3.8
Requires-Dist: click (>=7.1.1,<8.0.0)
Requires-Dist: diskcache (>=4.1.0,<5.0.0)
Requires-Dist: requests (>=2.23.0,<3.0.0)
